get_chefkoch/__init__.py
get_chefkoch/chefkoch.py
get_chefkoch/exceptions.py
get_chefkoch-1.0.2.dist-info/LICENSE
get_chefkoch-1.0.2.dist-info/METADATA
get_chefkoch-1.0.2.dist-info/WHEEL
get_chefkoch-1.0.2.dist-info/top_level.txt
get_chefkoch-1.0.2.dist-info/RECORD
