Metadata-Version: 2.1
Name: get-chefkoch
Version: 1.0.2
Summary: Python library to interact with Chefkoch.
Home-page: https://github.com/olzeug/get_chefkoch
Author: olzeug
License: MIT
Keywords: Chefkoch,get_chefkoch
Platform: UNKNOWN
Requires-Python: >=3.0
License-File: LICENSE
Requires-Dist: requests
Requires-Dist: feedparser
Requires-Dist: beautifulsoup4
